holocal/__init__.py
holocal/__main__.py
holocal/errors.py
holocal/event.py
holocal/parser.py
holocal/schedule.py
holocal/site.py
holocal/site_type.py
holocal-0.3.10.dist-info/METADATA
holocal-0.3.10.dist-info/WHEEL
holocal-0.3.10.dist-info/licenses/LICENSE
holocal-0.3.10.dist-info/RECORD
