Metadata-Version: 2.4
Name: holocal
Version: 0.3.10
Summary: This is an iCalendar generator for Holodule.
License-Expression: MIT
License-File: LICENSE
Keywords: schedule,holodule
Author: Sarisia
Author-email: git@sarisia.cc
Requires-Python: >=3.10,<4.0
Classifier: Programming Language :: Python :: 3
Classifier: Programming Language :: Python :: 3.10
Classifier: Programming Language :: Python :: 3.11
Classifier: Programming Language :: Python :: 3.12
Classifier: Programming Language :: Python :: 3.13
Classifier: Programming Language :: Python :: 3.14
Requires-Dist: aiohttp (>=3.11,<4.0)
Requires-Dist: aiohttp-client-cache[sqlite] (>=0.12.4,<0.13.0)
Requires-Dist: aiosqlite (>=0.20,<0.21)
Requires-Dist: ics (>=0.7.2,<0.8.0)
Requires-Dist: isodate (>=0.7.2,<0.8.0)
Requires-Dist: python-dotenv (>=0.15.0,<0.16.0)
Project-URL: Documentation, https://gemmaro.github.io/holocal/
Project-URL: Homepage, https://gemmaro.github.io/holocal/
Project-URL: changelog, https://gemmaro.github.io/holocal/CHANGELOG.html
Project-URL: issues, https://github.com/gemmaro/holocal/issues
Project-URL: source, https://github.com/gemmaro/holocal
